[
  {
    "name": "Meal 1",
    "picture": "https://example.com/meal1.jpg",
    "recipes": [
      {
        "name": "Recipe 1",
        "serving": 1,
        "ingredients": [],
        "steps": []
      },
      {
        "name": "Recipe 2",
        "ingredients": [
          {
            "name": "ingredient1",
            "amount": {
              "unit": "cup",
              "value": 1
            }
          },
          {
            "name": "ingredient2",
            "amount": {
              "unit": "cup",
              "value": 1
            }
          }
        ],
        "steps": [
          {
            "text": "Mix the thing",
            "duration": {
              "unit": "minutes",
              "value": 5
            }
          },
          {
            "text": "Cook the thing",
            "duration": {
              "unit": "hour",
              "value": 1
            }
          }
        ]
      }
    ]
  },
  {
    "name": "Meal 2",
    "picture": "https://example.com/meal2.jpg",
    "recipes": [
      {
        "name": "Recipe 1",
        "serving": 2,
        "ingredients": [
          {
            "name": "ingredient3",
            "amount": {
              "unit": "cup",
              "value": 2
            }
          },
          {
            "name": "ingredient4",
            "amount": {
              "unit": "teaspoon",
              "value": 3
            }
          },
          {
            "name": "ingredient5",
            "amount": {
              "unit": "tablespoon",
              "value": 1
            }
          }
        ],
        "steps": [
          {
            "text": "Preheat the oven",
            "duration": {
              "unit": "minutes",
              "value": 10
            }
          },
          {
            "text": "Mix all the ingredients",
            "duration": {
              "unit": "minutes",
              "value": 15
            }
          },
          {
            "text": "Bake for 30 minutes",
            "duration": {
              "unit": "minutes",
              "value": 30
            }
          }
        ]
      }
    ]
  },
  {
    "name": "Meal 3",
    "picture": "https://example.com/meal3.jpg",
    "recipes": [
      {
        "name": "Recipe 1",
        "serving": 4,
        "ingredients": [
          {
            "name": "ingredient6",
            "amount": {
              "unit": "cup",
              "value": 2.5
            }
          },
          {
            "name": "ingredient7",
            "amount": {
              "unit": "cup",
              "value": 1
            }
          },
          {
            "name": "ingredient8",
            "amount": {
              "unit": "tablespoon",
              "value": 2
            }
          },
          {
            "name": "ingredient9",
            "amount": {
              "unit": "teaspoon",
              "value": 0.5
            }
          }
        ],
        "steps": [
          {
            "text": "Boil water and add ingredient6",
            "duration": {
              "unit": "minutes",
              "value": 10
            }
          },
          {
            "text": "Stir in ingredient7 and cook for 5 minutes",
            "duration": {
              "unit": "minutes",
              "value": 5
            }
          },
          {
            "text": "Add ingredient8 and ingredient9 and cook for another 2 minutes",
            "duration": {
              "unit": "minutes",
              "value": 2
            }
          },
          {
            "text": "Serve hot",
            "duration": {
              "unit": "minutes",
              "value": 0
            }
          }
        ]
      }
    ]
  }
]
